README.md
setup.cfg
setup.py
django_ltree/__init__.py
django_ltree/apps.py
django_ltree/checks.py
django_ltree/fields.py
django_ltree/functions.py
django_ltree/lookups.py
django_ltree/managers.py
django_ltree/models.py
django_ltree/paths.py
django_ltree/migrations/0001_create_extension.py
django_ltree/migrations/__init__.py
django_ltree_fork.egg-info/PKG-INFO
django_ltree_fork.egg-info/SOURCES.txt
django_ltree_fork.egg-info/dependency_links.txt
django_ltree_fork.egg-info/requires.txt
django_ltree_fork.egg-info/top_level.txt