Metadata-Version: 2.1
Name: django-ltree-fork
Version: 0.4.5
Summary: django implemention of the ltree postgres extension - this is a backport to Python 2.7/Django 1.11
Home-page: https://github.com/boryszef/django-ltree
Author: Borys Szefczyk
Author-email: boryszef@gmail.com
License: MIT
Project-URL: Source, https://github.com/boryszef/django_ltree
Project-URL: Tracker, https://github.com/boryszef/django_ltree/issues
Platform: UNKNOWN
Classifier: Development Status :: 4 - Beta
Classifier: Framework :: Django
Classifier: Intended Audience :: Developers
Classifier: Operating System :: OS Independent
Classifier: Programming Language :: Python
Requires-Python: >=2.7
